dargor/Curses.py
dargor/DelayedKeyboardInterrupt.py
dargor/Tk.py
dargor/__init__.py
dargor/argparser.py
dargor/bench.py
dargor/coalesce.py
dargor/colored_tracebacks.py
dargor/console.py
dargor/dataclasses_helpers.py
dargor/deck.py
dargor/files.py
dargor/finance.py
dargor/nice.py
dargor/plots.py
dargor/pretty.py
dargor/py.typed
dargor/tuning.py
dargor-0.6.0.dist-info/LICENSE
dargor-0.6.0.dist-info/METADATA
dargor-0.6.0.dist-info/WHEEL
dargor-0.6.0.dist-info/top_level.txt
dargor-0.6.0.dist-info/RECORD
